flasked/__init__.py
flasked/metadata.py
flasked/core/__init__.py
flasked/core/flasked.py
flasked/handler/__init__.py
flasked/handler/route_handler.py
flasked/iterator/__init__.py
flasked/iterator/endpoint_matcher_iterator.py
flasked/utils/__init__.py
flasked/utils/helpers.py
flasked/warnings/__init__.py
flasked/warnings/warnings.py
Flasked-0.1.0.dist-info/AUTHORS
Flasked-0.1.0.dist-info/LICENSE
Flasked-0.1.0.dist-info/METADATA
Flasked-0.1.0.dist-info/WHEEL
Flasked-0.1.0.dist-info/top_level.txt
Flasked-0.1.0.dist-info/RECORD
