Metadata-Version: 2.1
Name: Flasked
Version: 0.1.0
Summary: A package designed to ease building HTTP REST APIs out-of-the-box, suitable for interactive environments like Jupyter Lab
Home-page: https://github.com/ipazc/flasked
Author: Iván de Paz Centeno
Author-email: ipazc@unileon.es
Classifier: Programming Language :: Python :: 3
Classifier: License :: OSI Approved :: MIT License
Classifier: Operating System :: OS Independent
Requires-Python: >=3.6
License-File: LICENSE
License-File: AUTHORS
Requires-Dist: Flask (>=3.0.2)
